{
  "opening": "catalan",
  "openingId": "catalan",
  "perspective": "white",
  "lines": [
    {
      "id": "catalan-line-0",
      "name": "open, classical line",
      "moves": [
        "d4",
        "Nf6",
        "c4",
        "e6",
        "g3",
        "d5",
        "Bg2",
        "dxc4",
        "Nf3",
        "Be7"
      ],
      "eco": "E05"
    },
    {
      "id": "catalan-line-1",
      "name": "open, Alekhine variation",
      "moves": [
        "d4",
        "Nf6",
        "c4",
        "e6",
        "g3",
        "d5",
        "Bg2",
        "dxc4",
        "Qa4+",
        "Nbd7",
        "Qxc4",
        "a6",
        "Qc2"
      ],
      "eco": "E03"
    },
    {
      "id": "catalan-line-2",
      "name": "closed, Botvinnik variation",
      "moves": [
        "d4",
        "Nf6",
        "c4",
        "e6",
        "g3",
        "d5",
        "Bg2",
        "Be7",
        "Nf3",
        "O-O",
        "O-O",
        "Nbd7",
        "Nc3",
        "c6",
        "Qd3"
      ],
      "eco": "E07"
    },
    {
      "id": "catalan-line-3",
      "name": "closed, Zagoryansky variation",
      "moves": [
        "d4",
        "Nf6",
        "c4",
        "e6",
        "g3",
        "d5",
        "Bg2",
        "Be7",
        "Nf3",
        "O-O",
        "O-O",
        "Nbd7",
        "Qc2",
        "c6",
        "Rd1",
        "b6",
        "a4"
      ],
      "eco": "E08"
    },
    {
      "id": "catalan-line-4",
      "name": "closed, Spassky gambit",
      "moves": [
        "d4",
        "Nf6",
        "c4",
        "e6",
        "g3",
        "d5",
        "Bg2",
        "Be7",
        "Nf3",
        "O-O",
        "O-O",
        "Nbd7",
        "Qc2",
        "c6",
        "b3",
        "b6",
        "Rd1",
        "Bb7",
        "Nc3",
        "b5"
      ],
      "eco": "E08"
    },
    {
      "id": "catalan-line-5",
      "name": "closed, Sokolsky variation",
      "moves": [
        "d4",
        "Nf6",
        "c4",
        "e6",
        "g3",
        "d5",
        "Bg2",
        "Be7",
        "Nf3",
        "O-O",
        "O-O",
        "Nbd7",
        "Qc2",
        "c6",
        "Nbd2",
        "b6",
        "b3",
        "a5",
        "Bb2",
        "Ba6"
      ],
      "eco": "E09"
    },
    {
      "id": "catalan-b6-bg2-bb7-bxb7-2yan5m",
      "name": "Bxb7 Line",
      "moves": [
        "b6",
        "Bg2",
        "Bb7",
        "Bxb7"
      ],
      "eco": "E00",
      "metadata": {
        "mistake_move_index": 0,
        "punishment_move_index": 1,
        "gameCounts": [
          76374,
          73523,
          1550,
          1370
        ],
        "winrates": [
          57.797810773299815,
          57.94445275628035,
          85.35483870967741,
          91.67883211678833
        ],
        "forcingSide": "white",
        "source": "lichess-db",
        "type": "forcing"
      }
    },
    {
      "id": "catalan-be7-nf3-d6-bg2-bd7-o-o-x5ua8z",
      "name": "cxd5 Line",
      "moves": [
        "Be7",
        "Nf3",
        "d6",
        "Bg2",
        "Bd7",
        "O-O",
        "Nc6",
        "d5",
        "exd5",
        "cxd5"
      ],
      "eco": "E00",
      "metadata": {
        "mistake_move_index": 0,
        "punishment_move_index": 1,
        "gameCounts": [
          66766,
          8017,
          8344,
          50544,
          3158,
          5987,
          3175,
          1562,
          1023,
          1029
        ],
        "winrates": [
          56.34679327801576,
          57.54022701758763,
          58.46116970278044,
          57.809037670148776,
          61.14629512349589,
          61.74210790045098,
          65.11811023622047,
          65.9090909090909,
          63.831867057673506,
          63.99416909620991
        ],
        "forcingSide": "white",
        "source": "lichess-db",
        "type": "forcing"
      }
    },
    {
      "id": "catalan-c6-nf3-bb4--bd2-bxd2--aj4by8",
      "name": "Bxd2 Line",
      "moves": [
        "c6",
        "Nf3",
        "Bb4+",
        "Bd2",
        "Bxd2+"
      ],
      "eco": "E00",
      "metadata": {
        "mistake_move_index": 0,
        "punishment_move_index": 1,
        "gameCounts": [
          34706,
          5368,
          2833,
          2038,
          1100
        ],
        "winrates": [
          57.8070074338731,
          60.81408345752608,
          59.1775503000353,
          59.592737978410206,
          60.22727272727273
        ],
        "forcingSide": "white",
        "source": "lichess-db",
        "type": "forcing"
      }
    },
    {
      "id": "catalan-nc6-nf3-b6-bg2-bb7-o-o-q0o0c8",
      "name": "Nc3 Line",
      "moves": [
        "Nc6",
        "Nf3",
        "b6",
        "Bg2",
        "Bb7",
        "O-O",
        "Bd6",
        "Nc3"
      ],
      "eco": "E00",
      "metadata": {
        "mistake_move_index": 0,
        "punishment_move_index": 1,
        "gameCounts": [
          11586,
          2660,
          3445,
          4564,
          13370,
          24699,
          1002,
          1256
        ],
        "winrates": [
          57.72915587778353,
          60.65789473684211,
          61.46589259796807,
          60.78001752848379,
          58.64248317127898,
          60.32835337463055,
          64.82035928143712,
          68.39171974522293
        ],
        "forcingSide": "white",
        "source": "lichess-db",
        "type": "forcing"
      }
    },
    {
      "id": "catalan-d6-nf3-nc6-bg2-d5-8929h2",
      "name": "d5 Line",
      "moves": [
        "d6",
        "Nf3",
        "Nc6",
        "Bg2",
        "d5"
      ],
      "eco": "E00",
      "metadata": {
        "mistake_move_index": 0,
        "punishment_move_index": 1,
        "gameCounts": [
          11382,
          2132,
          2391,
          6897,
          1166
        ],
        "winrates": [
          57.28782287822878,
          61.09287054409006,
          62.212463404433294,
          61.15702479338842,
          62.86449399656947
        ],
        "forcingSide": "white",
        "source": "lichess-db",
        "type": "forcing"
      }
    },
    {
      "id": "catalan-g6-nf3-bg7-bg2-d6-nc3-h34avm",
      "name": "e4 Line",
      "moves": [
        "g6",
        "Nf3",
        "Bg7",
        "Bg2",
        "d6",
        "Nc3",
        "Nc6",
        "O-O",
        "Bd7",
        "e4"
      ],
      "eco": "E00",
      "metadata": {
        "mistake_move_index": 0,
        "punishment_move_index": 1,
        "gameCounts": [
          11124,
          1063,
          14347,
          28469,
          3104,
          2447,
          1069,
          2746,
          1291,
          1444
        ],
        "winrates": [
          58.517619561308884,
          59.31326434619003,
          58.51397504704816,
          59.03263198566863,
          60.85695876288659,
          60.543522680833675,
          61.50608044901777,
          62.50910415149308,
          63.16808675445391,
          63.88504155124654
        ],
        "forcingSide": "white",
        "source": "lichess-db",
        "type": "forcing"
      }
    },
    {
      "id": "catalan-h6-bg2-d5-nf3-dxc4-o-o-5tpv7s",
      "name": "After Nc3 O-O e4",
      "moves": [
        "h6",
        "Bg2",
        "d5",
        "Nf3",
        "dxc4",
        "O-O",
        "Bd6",
        "Nc3",
        "O-O",
        "e4"
      ],
      "eco": "E00",
      "metadata": {
        "mistake_move_index": 0,
        "punishment_move_index": 1,
        "gameCounts": [
          3481,
          4263,
          1314,
          12555,
          9401,
          7821,
          1209,
          2759,
          1171,
          2626
        ],
        "winrates": [
          58.747486354495834,
          58.78489326765188,
          58.7138508371385,
          56.125049780963764,
          60.69035209020317,
          61.6800920598389,
          62.696443341604635,
          63.15694092062342,
          62.98035866780529,
          62.2048743335872
        ],
        "forcingSide": "white",
        "source": "lichess-db",
        "type": "forcing"
      }
    },
    {
      "id": "catalan-a6-bg2-d5-nf3-bb4--bd2-tl9o37",
      "name": "b5 Line",
      "moves": [
        "a6",
        "Bg2",
        "d5",
        "Nf3",
        "Bb4+",
        "Bd2",
        "Bxd2+",
        "Nbxd2",
        "O-O",
        "O-O",
        "dxc4",
        "Nxc4",
        "b5"
      ],
      "eco": "E00",
      "metadata": {
        "mistake_move_index": 0,
        "punishment_move_index": 1,
        "gameCounts": [
          2442,
          3068,
          1288,
          11035,
          4449,
          3333,
          1928,
          1680,
          1562,
          3958,
          1271,
          1470,
          1748
        ],
        "winrates": [
          60.483210483210485,
          59.680573663624514,
          56.25,
          55.79519710013593,
          60.800179815688914,
          60.486048604860486,
          62.00726141078838,
          63.24404761904761,
          63.0921895006402,
          62.34209196563921,
          66.16837136113297,
          66.59863945578232,
          66.90503432494279
        ],
        "forcingSide": "white",
        "source": "lichess-db",
        "type": "forcing"
      }
    },
    {
      "id": "catalan-d5-bg2-nc6-nf3-b6-o-o-79m2oa",
      "name": "Nxe5 Line",
      "moves": [
        "d5",
        "Bg2",
        "Nc6",
        "Nf3",
        "b6",
        "O-O",
        "dxc4",
        "Ne5",
        "Nxe5"
      ],
      "eco": "E00",
      "metadata": {
        "mistake_move_index": 1,
        "punishment_move_index": 2,
        "gameCounts": [
          905649,
          1168956,
          30409,
          33775,
          7532,
          5332,
          1440,
          1634,
          1096
        ],
        "winrates": [
          54.73168965018457,
          55.023542374563284,
          57.85293827485284,
          59.030347890451516,
          63.15055762081785,
          64.14103525881471,
          73.95833333333334,
          79.52876376988985,
          73.90510948905109
        ],
        "forcingSide": "white",
        "source": "lichess-db",
        "type": "forcing"
      }
    },
    {
      "id": "catalan-d5-nf3-nc6-nbd2-bb4-bg2-hv17v2",
      "name": "Nxd2 Line",
      "moves": [
        "d5",
        "Nf3",
        "Nc6",
        "Nbd2",
        "Bb4",
        "Bg2",
        "Ne4",
        "O-O",
        "Nxd2"
      ],
      "eco": "E00",
      "metadata": {
        "mistake_move_index": 1,
        "punishment_move_index": 2,
        "gameCounts": [
          905649,
          331016,
          100963,
          2554,
          2159,
          4806,
          2432,
          2537,
          1255
        ],
        "winrates": [
          54.73168965018457,
          55.81270995963942,
          60.83961451224707,
          62.19655442443226,
          61.185734136174155,
          61.52725759467332,
          62.99342105263158,
          62.77098935750887,
          63.86454183266932
        ],
        "forcingSide": "white",
        "source": "lichess-db",
        "type": "forcing"
      }
    },
    {
      "id": "catalan-d5-bg2-c6-qc2-bb4--bd2-3mlvdr",
      "name": "Rfd1 Line",
      "moves": [
        "d5",
        "Bg2",
        "c6",
        "Qc2",
        "Bb4+",
        "Bd2",
        "Bxd2+",
        "Nxd2",
        "O-O",
        "Ngf3",
        "Re8",
        "O-O",
        "Nbd7",
        "Rfd1"
      ],
      "eco": "E00",
      "metadata": {
        "mistake_move_index": 2,
        "punishment_move_index": 3,
        "gameCounts": [
          905649,
          1168956,
          326690,
          19709,
          3069,
          2146,
          1319,
          1314,
          1398,
          1909,
          1267,
          1204,
          5582,
          3883
        ],
        "winrates": [
          54.73168965018457,
          55.023542374563284,
          55.933300682604305,
          58.343903800294285,
          60.58976865428478,
          59.69245107176142,
          59.9696739954511,
          60.0076103500761,
          59.76394849785408,
          60.18858040859089,
          62.904498816101025,
          63.95348837209303,
          62.20888570404873,
          63.26294102498069
        ],
        "forcingSide": "white",
        "source": "lichess-db",
        "type": "forcing"
      }
    },
    {
      "id": "catalan-d5-bg2-bb4--nd2-dxc4-qa4--bkfgu5",
      "name": "Qxb4 Line",
      "moves": [
        "d5",
        "Bg2",
        "Bb4+",
        "Nd2",
        "dxc4",
        "Qa4+",
        "Nc6",
        "Bxc6+",
        "bxc6",
        "Qxb4"
      ],
      "eco": "E00",
      "metadata": {
        "mistake_move_index": 2,
        "punishment_move_index": 3,
        "gameCounts": [
          905649,
          1168956,
          176893,
          40193,
          6341,
          3942,
          2626,
          2556,
          2278,
          2251
        ],
        "winrates": [
          54.73168965018457,
          55.023542374563284,
          55.26024206723839,
          57.80981762993556,
          75.20895757766914,
          87.3795027904617,
          84.13937547600914,
          84.9960876369327,
          83.36259877085162,
          83.54064860062195
        ],
        "forcingSide": "white",
        "source": "lichess-db",
        "type": "forcing"
      }
    },
    {
      "id": "catalan-d5-bg2-b6-cxd5-bb7-p09uq5",
      "name": "Bb7 Line",
      "moves": [
        "d5",
        "Bg2",
        "b6",
        "cxd5",
        "Bb7"
      ],
      "eco": "E00",
      "metadata": {
        "mistake_move_index": 2,
        "punishment_move_index": 3,
        "gameCounts": [
          905649,
          1168956,
          49711,
          17977,
          1260
        ],
        "winrates": [
          54.73168965018457,
          55.023542374563284,
          55.359980688378826,
          58.08533125660566,
          59.72222222222222
        ],
        "forcingSide": "white",
        "source": "lichess-db",
        "type": "forcing"
      }
    },
    {
      "id": "catalan-d5-bg2-bd6-nf3-qe7-j6zu64",
      "name": "Qe7 Line",
      "moves": [
        "d5",
        "Bg2",
        "Bd6",
        "Nf3",
        "Qe7"
      ],
      "eco": "E00",
      "metadata": {
        "mistake_move_index": 2,
        "punishment_move_index": 3,
        "gameCounts": [
          905649,
          1168956,
          31215,
          17881,
          1188
        ],
        "winrates": [
          54.73168965018457,
          55.023542374563284,
          56.28704148646484,
          58.24897936357027,
          65.44612794612794
        ],
        "forcingSide": "white",
        "source": "lichess-db",
        "type": "forcing"
      }
    },
    {
      "id": "catalan-d5-bg2-nbd7-nf3-c5-cxd5-j2dxfy",
      "name": "c4 Line",
      "moves": [
        "d5",
        "Bg2",
        "Nbd7",
        "Nf3",
        "c5",
        "cxd5",
        "exd5",
        "O-O",
        "c4"
      ],
      "eco": "E00",
      "metadata": {
        "mistake_move_index": 2,
        "punishment_move_index": 3,
        "gameCounts": [
          905649,
          1168956,
          23279,
          17168,
          16568,
          8580,
          4786,
          4327,
          1187
        ],
        "winrates": [
          54.73168965018457,
          55.023542374563284,
          55.19996563426264,
          56.21213886300092,
          58.6341139546113,
          59.98834498834499,
          60.26953614709569,
          60.97758262075341,
          63.39511373209773
        ],
        "forcingSide": "white",
        "source": "lichess-db",
        "type": "forcing"
      }
    },
    {
      "id": "catalan-d5-bg2-g6-nf3-dxc4-o-o-kv3gff",
      "name": "Na3 Line",
      "moves": [
        "d5",
        "Bg2",
        "g6",
        "Nf3",
        "dxc4",
        "O-O",
        "Bg7",
        "Na3"
      ],
      "eco": "E00",
      "metadata": {
        "mistake_move_index": 2,
        "punishment_move_index": 3,
        "gameCounts": [
          905649,
          1168956,
          13097,
          10175,
          1573,
          4238,
          3769,
          1070
        ],
        "winrates": [
          54.73168965018457,
          55.023542374563284,
          56.71527830800947,
          57.7985257985258,
          62.174189446916714,
          63.048607833883906,
          62.81507031042717,
          68.97196261682244
        ],
        "forcingSide": "white",
        "source": "lichess-db",
        "type": "forcing"
      }
    },
    {
      "id": "catalan-d5-bg2-a6-nf3-bb4--bd2-tshedh",
      "name": "After dxc4 Nxc4 b5",
      "moves": [
        "d5",
        "Bg2",
        "a6",
        "Nf3",
        "Bb4+",
        "Bd2",
        "Bxd2+",
        "Nbxd2",
        "O-O",
        "O-O",
        "dxc4",
        "Nxc4",
        "b5"
      ],
      "eco": "E00",
      "metadata": {
        "mistake_move_index": 2,
        "punishment_move_index": 3,
        "gameCounts": [
          905649,
          1168956,
          12693,
          11035,
          4449,
          3333,
          1928,
          1680,
          1562,
          3958,
          1271,
          1470,
          1748
        ],
        "winrates": [
          54.73168965018457,
          55.023542374563284,
          55.239108169857396,
          55.79519710013593,
          60.800179815688914,
          60.486048604860486,
          62.00726141078838,
          63.24404761904761,
          63.0921895006402,
          62.34209196563921,
          66.16837136113297,
          66.59863945578232,
          66.90503432494279
        ],
        "forcingSide": "white",
        "source": "lichess-db",
        "type": "forcing"
      }
    },
    {
      "id": "catalan-d5-bg2-be7-nf3-c6-nbd2-59aixh",
      "name": "Nxe4 Line",
      "moves": [
        "d5",
        "Bg2",
        "Be7",
        "Nf3",
        "c6",
        "Nbd2",
        "Nbd7",
        "Qc2",
        "b6",
        "O-O",
        "Bb7",
        "e4",
        "dxe4",
        "Nxe4"
      ],
      "eco": "E00",
      "metadata": {
        "mistake_move_index": 4,
        "punishment_move_index": 5,
        "gameCounts": [
          905649,
          1168956,
          404161,
          337053,
          147894,
          21808,
          8560,
          2814,
          1480,
          1392,
          8176,
          13264,
          10208,
          10119
        ],
        "winrates": [
          54.73168965018457,
          55.023542374563284,
          53.363387362956836,
          54.03705055288041,
          57.58989546567136,
          59.2236793837124,
          60.11682242990655,
          60.3411513859275,
          62.22972972972973,
          62.679597701149426,
          60.20670254403131,
          60.71320868516285,
          61.29506269592476,
          61.31040616661726
        ],
        "forcingSide": "white",
        "source": "lichess-db",
        "type": "forcing"
      }
    },
    {
      "id": "catalan-d5-bg2-be7-nf3-dxc4-nbd2-lr897f",
      "name": "Nce5 Line",
      "moves": [
        "d5",
        "Bg2",
        "Be7",
        "Nf3",
        "dxc4",
        "Nbd2",
        "O-O",
        "O-O",
        "Nc6",
        "Nxc4",
        "b5",
        "Nce5"
      ],
      "eco": "E00",
      "metadata": {
        "mistake_move_index": 4,
        "punishment_move_index": 5,
        "gameCounts": [
          905649,
          1168956,
          404161,
          337053,
          87264,
          3749,
          2396,
          1335,
          6136,
          12980,
          2019,
          1301
        ],
        "winrates": [
          54.73168965018457,
          55.023542374563284,
          53.363387362956836,
          54.03705055288041,
          57.291666666666664,
          58.52227260602827,
          58.702003338898166,
          60.48689138576779,
          61.57920469361148,
          63.52850539291217,
          69.26696384348688,
          69.21598770176787
        ],
        "forcingSide": "white",
        "source": "lichess-db",
        "type": "forcing"
      }
    },
    {
      "id": "catalan-d5-bg2-be7-nf3-b6-cxd5-v9n36m",
      "name": "Rc1 Line",
      "moves": [
        "d5",
        "Bg2",
        "Be7",
        "Nf3",
        "b6",
        "cxd5",
        "exd5",
        "O-O",
        "O-O",
        "Bf4",
        "Bb7",
        "Nc3",
        "Ne4",
        "Rc1"
      ],
      "eco": "E00",
      "metadata": {
        "mistake_move_index": 4,
        "punishment_move_index": 5,
        "gameCounts": [
          905649,
          1168956,
          404161,
          337053,
          50689,
          7785,
          4966,
          5867,
          3608,
          3242,
          2536,
          2520,
          2785,
          1730
        ],
        "winrates": [
          54.73168965018457,
          55.023542374563284,
          53.363387362956836,
          54.03705055288041,
          56.538894040127055,
          59.38342967244702,
          60.54168344744261,
          60.20964717913755,
          60.684589800443455,
          59.63911165946947,
          58.63564668769716,
          60.37698412698413,
          61.992818671454216,
          63.93063583815029
        ],
        "forcingSide": "white",
        "source": "lichess-db",
        "type": "forcing"
      }
    },
    {
      "id": "catalan-d5-bg2-be7-nf3-nbd7-qc2-8k0yzl",
      "name": "Qc2 Line",
      "moves": [
        "d5",
        "Bg2",
        "Be7",
        "Nf3",
        "Nbd7",
        "Qc2"
      ],
      "eco": "E00",
      "metadata": {
        "mistake_move_index": 4,
        "punishment_move_index": 5,
        "gameCounts": [
          905649,
          1168956,
          404161,
          337053,
          47056,
          2791
        ],
        "winrates": [
          54.73168965018457,
          55.023542374563284,
          53.363387362956836,
          54.03705055288041,
          57.459197551853116,
          58.258688642063774
        ],
        "forcingSide": "white",
        "source": "lichess-db",
        "type": "forcing"
      }
    }
  ],
  "generatedAt": "2026-02-08T02:24:57.064Z"
}